{
	"id": "bb089fe0-66f9-49c1-b85b-6ddac93c6390",
	"name": "Shop_Local",
	"values": [
		{
			"key": "ENDPOINT",
			"value": "http://localhost:9090",
			"type": "default",
			"enabled": true
		},
		{
			"key": "TOKEN",
			"value": "Bearer eyJhbGciOiJIUzI1NiJ9.eyJzdWIiOiJhZG1pbkBnbWFpbC5jb20iLCJpYXQiOjE2OTg4MDAxNjEsImV4cCI6MTY5ODg4NjU2MX0.jlYRkIiF5rZWquyb-W6tIaoHNYOJy5JwpFuHifaVC6M",
			"type": "any",
			"enabled": true
		}
	],
	"_postman_variable_scope": "environment",
	"_postman_exported_at": "2023-11-01T09:43:41.621Z",
	"_postman_exported_using": "Postman/10.19.10"
}